midigen/__init__.py
midigen/generate.py
midigen/humanize.py
midigen/instrument_map.csv
midigen/instruments.py
midigen/keys.py
midigen/markov.py
midigen/midigen.als
midigen/notes.py
midigen/percussion_map.csv
midigen/rhythm.py
midigen/sequencer.py
midigen/time.py
midigen-0.0.13.dist-info/LICENSE
midigen-0.0.13.dist-info/METADATA
midigen-0.0.13.dist-info/WHEEL
midigen-0.0.13.dist-info/entry_points.txt
midigen-0.0.13.dist-info/top_level.txt
midigen-0.0.13.dist-info/RECORD
