Metadata-Version: 2.1
Name: midigen
Version: 0.0.13
Author-email: Bryan Johnson <d.bryan.johnson@gmail.com>
License: MIT License
Project-URL: Homepage, https://github.com/dbjohnson/midigen
Keywords: midi,generative,audio,music
Classifier: License :: OSI Approved :: MIT License
Classifier: Programming Language :: Python
Classifier: Programming Language :: Python :: 3
Requires-Python: >=3.6
License-File: LICENSE
Requires-Dist: mido>=1.2.10
Requires-Dist: python-rtmidi>=1.4.9
Requires-Dist: setuptools
Provides-Extra: dev
Requires-Dist: bumpver; extra == "dev"
Requires-Dist: pytest; extra == "dev"
Requires-Dist: build; extra == "dev"
Requires-Dist: twine; extra == "dev"
